{
  "$schema": "http://iglucentral.com/schemas/com.snowplowanalytics.self-desc/schema/jsonschema/1-0-0#",
  "description": "Schema for a page view context",
  "self": {
    "vendor": "com.innohead",
    "name": "snow_page_context",
    "format": "jsonschema",
    "version": "1-0-0"
  },

  "type": "object",
  "properties": {
    "timestamp": {
      "type": "integer"
    },
    "event_type": {
      "type": "string"
    },
    "page_title": {
      "type": "string"
    }
  },
  "required": ["timestamp"],
  "additionalProperties": false
}